serde/__init__.py
serde/compat.py
serde/core.py
serde/de.py
serde/inspect.py
serde/json.py
serde/msgpack.py
serde/numpy.py
serde/pickle.py
serde/py.typed
serde/se.py
serde/sqlalchemy.py
serde/toml.py
serde/yaml.py
pyserde-0.29.1.dist-info/METADATA
pyserde-0.29.1.dist-info/WHEEL
pyserde-0.29.1.dist-info/licenses/LICENSE
pyserde-0.29.1.dist-info/RECORD
