Metadata-Version: 2.4
Name: pyserde
Version: 0.29.1
Summary: Yet another serialization library on top of dataclasses
Project-URL: Repository, https://github.com/yukinarit/pyserde
Project-URL: Homepage, https://github.com/yukinarit/pyserde
Author-email: yukinarit <yukinarit84@gmail.com>
License: MIT License
License-File: LICENSE
Classifier: Development Status :: 5 - Production/Stable
Classifier: Intended Audience :: Developers
Classifier: License :: OSI Approved :: MIT License
Classifier: Programming Language :: Python :: 3.10
Classifier: Programming Language :: Python :: 3.11
Classifier: Programming Language :: Python :: 3.12
Classifier: Programming Language :: Python :: 3.13
Classifier: Programming Language :: Python :: 3.14
Classifier: Programming Language :: Python :: Implementation :: CPython
Classifier: Programming Language :: Python :: Implementation :: PyPy
Requires-Python: <4.0,>=3.10
Requires-Dist: beartype>=0.18.4
Requires-Dist: casefy
Requires-Dist: jinja2
Requires-Dist: plum-dispatch>=2.3
Requires-Dist: typing-extensions<4.16.0,>=4.1.0
Requires-Dist: typing-inspect>=0.4.0
Provides-Extra: all
Requires-Dist: jaxtyping<0.3.0; extra == 'all'
Requires-Dist: msgpack; extra == 'all'
Requires-Dist: numpy<3.0.0,>1.22.0; extra == 'all'
Requires-Dist: orjson; extra == 'all'
Requires-Dist: pyyaml; extra == 'all'
Requires-Dist: sqlalchemy>2; extra == 'all'
Requires-Dist: tomli-w; extra == 'all'
Requires-Dist: tomli; (python_version < '3.11') and extra == 'all'
Provides-Extra: jaxtyping
Requires-Dist: jaxtyping<0.3.0; extra == 'jaxtyping'
Provides-Extra: msgpack
Requires-Dist: msgpack; extra == 'msgpack'
Provides-Extra: numpy
Requires-Dist: numpy<3.0.0,>1.22.0; extra == 'numpy'
Provides-Extra: orjson
Requires-Dist: orjson; extra == 'orjson'
Provides-Extra: sqlalchemy
Requires-Dist: sqlalchemy>2; extra == 'sqlalchemy'
Provides-Extra: toml
Requires-Dist: tomli-w; extra == 'toml'
Requires-Dist: tomli; (python_version < '3.11') and extra == 'toml'
Provides-Extra: yaml
Requires-Dist: pyyaml; extra == 'yaml'
